passiogo/__init__.py
tests/__init__.py
tests/test_main.py
passiogo_up-0.2.3.dist-info/LICENSE
passiogo_up-0.2.3.dist-info/METADATA
passiogo_up-0.2.3.dist-info/WHEEL
passiogo_up-0.2.3.dist-info/top_level.txt
passiogo_up-0.2.3.dist-info/RECORD
