Metadata-Version: 2.2
Name: PassioGo_up
Version: 0.2.3
Summary: An unofficial API for Passio Go
Home-page: https://github.com/athuler/PassioGo
Author: Andrei Thuler
Author-email: info@andreithuler.com
Project-URL: Documentation, https://passiogo.readthedocs.io/
Project-URL: GitHub, https://github.com/athuler/PassioGo
Project-URL: Sponsor, https://github.com/sponsors/athuler
Project-URL: Changelog, https://github.com/athuler/PassioGo/blob/main/CHANGELOG.md
License-File: LICENSE
Requires-Dist: requests>=2.22.0
Requires-Dist: websocket-client>=1.2.0
Dynamic: author
Dynamic: author-email
Dynamic: description
Dynamic: description-content-type
Dynamic: home-page
Dynamic: project-url
Dynamic: requires-dist
Dynamic: summary
